[
  {
    "text": "intellectual",
    "size": 35
  },
  {
    "text": "muslim",
    "size": 31
  },
  {
    "text": "religious",
    "size": 30
  },
  {
    "text": "islamic",
    "size": 21
  },
  {
    "text": "context",
    "size": 20
  },
  {
    "text": "religion",
    "size": 15
  },
  {
    "text": "knowledge",
    "size": 14
  },
  {
    "text": "practice",
    "size": 13
  },
  {
    "text": "social",
    "size": 13
  },
  {
    "text": "new",
    "size": 13
  },
  {
    "text": "culture",
    "size": 12
  },
  {
    "text": "life",
    "size": 12
  },
  {
    "text": "world",
    "size": 12
  },
  {
    "text": "way",
    "size": 11
  },
  {
    "text": "region",
    "size": 11
  },
  {
    "text": "theological",
    "size": 11
  },
  {
    "text": "arab",
    "size": 11
  },
  {
    "text": "different",
    "size": 10
  },
  {
    "text": "tradition",
    "size": 10
  },
  {
    "text": "network",
    "size": 10
  },
  {
    "text": "discourse",
    "size": 10
  },
  {
    "text": "idea",
    "size": 10
  },
  {
    "text": "society",
    "size": 9
  },
  {
    "text": "secular",
    "size": 9
  },
  {
    "text": "education",
    "size": 9
  },
  {
    "text": "actor",
    "size": 9
  },
  {
    "text": "theology",
    "size": 9
  },
  {
    "text": "religiosity",
    "size": 8
  },
  {
    "text": "critical",
    "size": 8
  },
  {
    "text": "academic",
    "size": 8
  },
  {
    "text": "school",
    "size": 8
  },
  {
    "text": "africa",
    "size": 8
  },
  {
    "text": "role",
    "size": 8
  },
  {
    "text": "elite",
    "size": 8
  },
  {
    "text": "heshmat",
    "size": 8
  },
  {
    "text": "particular",
    "size": 7
  },
  {
    "text": "dynamic",
    "size": 7
  },
  {
    "text": "work",
    "size": 7
  },
  {
    "text": "local",
    "size": 7
  },
  {
    "text": "time",
    "size": 7
  },
  {
    "text": "christianity",
    "size": 7
  },
  {
    "text": "state",
    "size": 7
  },
  {
    "text": "west",
    "size": 7
  },
  {
    "text": "seek",
    "size": 7
  },
  {
    "text": "islam",
    "size": 7
  },
  {
    "text": "public",
    "size": 7
  },
  {
    "text": "vr",
    "size": 7
  },
  {
    "text": "specific",
    "size": 6
  },
  {
    "text": "process",
    "size": 6
  },
  {
    "text": "traditional",
    "size": 6
  },
  {
    "text": "question",
    "size": 6
  },
  {
    "text": "individual",
    "size": 6
  },
  {
    "text": "examine",
    "size": 6
  },
  {
    "text": "form",
    "size": 6
  },
  {
    "text": "political",
    "size": 6
  },
  {
    "text": "system",
    "size": 6
  },
  {
    "text": "south",
    "size": 6
  },
  {
    "text": "investigates",
    "size": 6
  },
  {
    "text": "western",
    "size": 6
  },
  {
    "text": "art",
    "size": 6
  },
  {
    "text": "student",
    "size": 6
  },
  {
    "text": "university",
    "size": 6
  },
  {
    "text": "deobandi",
    "size": 6
  },
  {
    "text": "periodical",
    "size": 6
  },
  {
    "text": "relation",
    "size": 5
  },
  {
    "text": "concern",
    "size": 5
  },
  {
    "text": "ethnographic",
    "size": 5
  },
  {
    "text": "approach",
    "size": 5
  },
  {
    "text": "language",
    "size": 5
  },
  {
    "text": "human",
    "size": 5
  },
  {
    "text": "challenge",
    "size": 5
  },
  {
    "text": "various",
    "size": 5
  },
  {
    "text": "engagement",
    "size": 5
  },
  {
    "text": "beyond",
    "size": 5
  },
  {
    "text": "global",
    "size": 5
  },
  {
    "text": "influence",
    "size": 5
  },
  {
    "text": "concept",
    "size": 5
  },
  {
    "text": "thought",
    "size": 5
  },
  {
    "text": "modern",
    "size": 5
  },
  {
    "text": "anthropology",
    "size": 5
  },
  {
    "text": "egyptian",
    "size": 5
  },
  {
    "text": "campus",
    "size": 5
  },
  {
    "text": "press",
    "size": 5
  },
  {
    "text": "tatar",
    "size": 5
  },
  {
    "text": "hybrid",
    "size": 5
  },
  {
    "text": "focus",
    "size": 4
  },
  {
    "text": "understanding",
    "size": 4
  },
  {
    "text": "reflect",
    "size": 4
  },
  {
    "text": "well",
    "size": 4
  },
  {
    "text": "regional",
    "size": 4
  },
  {
    "text": "interest",
    "size": 4
  },
  {
    "text": "method",
    "size": 4
  },
  {
    "text": "aspect",
    "size": 4
  },
  {
    "text": "recent",
    "size": 4
  },
  {
    "text": "use",
    "size": 4
  },
  {
    "text": "digital",
    "size": 4
  },
  {
    "text": "view",
    "size": 4
  },
  {
    "text": "christian",
    "size": 4
  },
  {
    "text": "living",
    "size": 4
  },
  {
    "text": "emerged",
    "size": 4
  }
]